validations_engine/GchatHelper.py
validations_engine/SlackHelper.py
validations_engine/__init__.py
validations_engine/base_validation_suites_executor.py
validations_engine/message.py
validations_engine/validations_engine.py
validations_engine-2.0.0.dist-info/METADATA
validations_engine-2.0.0.dist-info/WHEEL
validations_engine-2.0.0.dist-info/top_level.txt
validations_engine-2.0.0.dist-info/RECORD
