Metadata-Version: 2.1
Name: validations-engine
Version: 2.0.0
Summary: Engine for creating and running validation suites for general purposes
Home-page: https://github.com/quintoandar/validations-engine
Author: QuintoAndar
License: UNKNOWN
Keywords: python,validations,validations-engine
Platform: UNKNOWN
Classifier: Natural Language :: English
Classifier: Programming Language :: Python :: 3
Classifier: Programming Language :: Python :: 3.7
Classifier: Programming Language :: Python :: 3.8
Requires-Python: >=3.7, <4
Requires-Dist: requests (==2.28.1)
